cli.py
core/__init__.py
core/batching.py
core/checksum.py
core/context.py
core/engine.py
core/metrics.py
core/schema.py
core/schema_diff.py
core/state.py
core/syncer.py
core/worker.py
syncset_db-0.2.0.dist-info/licenses/LICENSE
syncset_db-0.2.0.dist-info/METADATA
syncset_db-0.2.0.dist-info/WHEEL
syncset_db-0.2.0.dist-info/entry_points.txt
syncset_db-0.2.0.dist-info/top_level.txt
syncset_db-0.2.0.dist-info/RECORD
