Metadata-Version: 2.4
Name: syncset-db
Version: 0.2.0
Summary: A powerful database replication and synchronization tool
Author-email: Mohamed Aklamaash <aklamaash78@gmail.com>
Project-URL: Homepage, https://github.com/MohamedAklamaash/syncset
Project-URL: Bug Tracker, https://github.com/MohamedAklamaash/syncset/issues
Classifier: Programming Language :: Python :: 3
Classifier: License :: OSI Approved :: MIT License
Classifier: Operating System :: OS Independent
Requires-Python: >=3.8
License-File: LICENSE
Requires-Dist: sqlalchemy>=2.0.0
Requires-Dist: psycopg2-binary>=2.9.0
Requires-Dist: pyyaml>=6.0.0
Dynamic: license-file
